redisw/__init__.py
redisw/pubsub.py
redisw/queue.py
redisw-0.1.4.dist-info/METADATA
redisw-0.1.4.dist-info/WHEEL
redisw-0.1.4.dist-info/top_level.txt
redisw-0.1.4.dist-info/RECORD
