Metadata-Version: 2.4
Name: redisw
Version: 0.1.4
Summary: Add your description here
Requires-Python: >=3.10
Requires-Dist: redis>=5.2.1
